shifrator/__init__.py
bit_shifrator-0.5.dist-info/METADATA
bit_shifrator-0.5.dist-info/WHEEL
bit_shifrator-0.5.dist-info/top_level.txt
bit_shifrator-0.5.dist-info/RECORD
