Metadata-Version: 2.1
Name: bit-shifrator
Version: 0.5
Summary: This is a bit-encoder module
Home-page: https://github.com/michazaxm/shifrator
Author: michazaxm
Author-email: michazaxm@gmail.com
License: UNKNOWN
Platform: UNKNOWN
Classifier: Programming Language :: Python :: 3.9
Requires-Python: >=3.9
